{
  "parent": "hexalia:root",
  "criteria": {
    "use_clear_idol": {
      "conditions": {
        "item": {
          "items": [
            "hexalia:clear_idol"
          ]
        }
      },
      "trigger": "minecraft:consume_item"
    },
    "use_rain_idol": {
      "conditions": {
        "item": {
          "items": [
            "hexalia:rain_idol"
          ]
        }
      },
      "trigger": "minecraft:consume_item"
    },
    "use_storm_idol": {
      "conditions": {
        "item": {
          "items": [
            "hexalia:storm_idol"
          ]
        }
      },
      "trigger": "minecraft:consume_item"
    }
  },
  "display": {
    "announce_to_chat": true,
    "background": "hexalia:textures/block/willow_log.png",
    "description": {
      "translate": "advancements.hexalia.weather_idol.description"
    },
    "frame": "task",
    "hidden": false,
    "icon": {
      "item": "hexalia:storm_idol"
    },
    "show_toast": true,
    "title": {
      "translate": "advancements.hexalia.weather_idol.title"
    }
  },
  "requirements": [
    [
      "use_weather_idol",
      "use_clear_idol",
      "use_storm_idol"
    ]
  ],
  "sends_telemetry_event": true
}